ödev1/mux5x1.v
module Mux5x1 #(parameter N = 32) (
    input  wire [N-1:0] In_AddResult,
    input  wire [N-1:0] In_SubResult,
    input  wire [N-1:0] In_AndResult,
    input  wire [N-1:0] In_XorResult,
    input  wire [N-1:0] In_SltResult,
    input  wire [2:0]   Sel,
    output reg [N-1:0] Out
);

    always @(*) begin
        case (Sel)
            3'b000:  Out = In_AddResult;
            3'b001:  Out = In_SubResult;
            3'b010:  Out = In_AndResult;
            3'b011:  Out = In_XorResult;
            3'b101:  Out = In_SltResult;
            default: Out = {N{1'bx}};
        endcase
    end

endmodule

ödev1/slt.v
module SLT #(parameter N = 32) (
    input  wire Sum_MSB,
    input  wire Overflow,
    output wire [N-1:0] SLT_Result
);

    wire slt_bit;
    assign slt_bit = Sum_MSB ^ Overflow;

    assign SLT_Result = {{(N-1){1'b0}}, slt_bit};

endmodule

ödev1/xor.v
module XOR #(parameter N = 32) (
    input  wire [N-1:0] A,
    input  wire [N-1:0] B,
    output wire [N-1:0] Result
);

    assign Result = A ^ B;

endmodule

ödev1/and.v
module AND #(parameter N = 32) (
    input  wire [N-1:0] A,
    input  wire [N-1:0] B,
    output wire [N-1:0] Result
);

    assign Result = A & B;

endmodule

ödev1/adder.v
module Adder #(parameter N = 32) (
    input  wire [N-1:0] A,
    input  wire [N-1:0] B,
    input  wire         Cin,
    output wire [N-1:0] Sum,
    output wire         Cout
);

    assign {Cout, Sum} = {1'b0, A} + {1'b0, B} + Cin;

endmodule

ödev1/alu.v
`include "adder.v"
`include "and.v"
`include "xor.v"
`include "slt.v"
`include "mux5x1.v"

module ALU #(parameter N = 32) (
    input  wire [N-1:0] A,
    input  wire [N-1:0] B,
    input  wire [2:0]   ALUControl,
    output wire [N-1:0] Result,
    output wire         oVerflow
);

    wire [N-1:0] B_operand;
    wire         Cin;
    wire [N-1:0] adder_sum;
    wire         adder_cout;
    wire [N-1:0] and_result;
    wire [N-1:0] xor_result;
    wire [N-1:0] slt_result;


    assign B_operand = B ^ {N{ALUControl[0]}};
    assign Cin = ALUControl[0];


    Adder #(.N(N)) adder_unit (
        .A(A),
        .B(B_operand),
        .Cin(Cin),
        .Sum(adder_sum),
        .Cout(adder_cout)
    );


    assign oVerflow = (~(A[N-1] ^ B[N-1] ^ ALUControl[0])) & (A[N-1] ^ adder_sum[N-1]) & (~ALUControl[1]);


    AND #(.N(N)) and_unit (
        .A(A),
        .B(B),
        .Result(and_result)
    );


    XOR #(.N(N)) xor_unit (
        .A(A),
        .B(B),
        .Result(xor_result)
    );


    SLT #(.N(N)) slt_unit (
        .Sum_MSB(adder_sum[N-1]),
        .Overflow(oVerflow),
        .SLT_Result(slt_result)
    );


    Mux5x1 #(.N(N)) output_mux (
        .In_AddResult(adder_sum),
        .In_SubResult(adder_sum),
        .In_AndResult(and_result),
        .In_XorResult(xor_result),
        .In_SltResult(slt_result),
        .Sel(ALUControl),
        .Out(Result)
    );

endmodule

ödev1/alu_tb.v
`include "alu.v"
`timescale 1ns/1ps

module ALU_tb;

    localparam N = 32;

    reg [N-1:0] tb_A;
    reg [N-1:0] tb_B;
    reg [2:0]   tb_ALUControl;
    wire [N-1:0] tb_Result;
    wire         tb_oVerflow;


    ALU #(.N(N)) uut (
        .A(tb_A),
        .B(tb_B),
        .ALUControl(tb_ALUControl),
        .Result(tb_Result),
        .oVerflow(tb_oVerflow)
    );


    initial begin

        $dumpfile("alu_tb.vcd");
        $dumpvars(0, ALU_tb);

        tb_A = 32'b0;
        tb_B = 32'b0;
        tb_ALUControl = 3'b000;
        #5;


        $display("--- ADD Testleri (000) ---");
        tb_ALUControl = 3'b000;
        tb_A = 32'd10;      tb_B = 32'd5;      #10;
        tb_A = 32'd10;      tb_B = 32'hFFFF_FFFB;  #10;
        tb_A = 32'hFFFF_FFF6;  tb_B = 32'd5;      #10;
        tb_A = 32'hFFFF_FFF6;  tb_B = 32'hFFFF_FFFB;  #10;

        tb_A = 32'h7FFFFFFF;tb_B = 32'd1;      #10;
        tb_A = 32'h80000000;tb_B = 32'h80000000;#10;

        $display("--- SUB Testleri (001) ---");
        tb_ALUControl = 3'b001;
        tb_A = 32'd10;      tb_B = 32'd5;      #10;
        tb_A = 32'd5;       tb_B = 32'd10;     #10;
        tb_A = 32'd10;      tb_B = 32'hFFFF_FFFB;  #10;
        tb_A = 32'hFFFF_FFF6;  tb_B = 32'd5;      #10;
        tb_A = 32'hFFFF_FFF6;  tb_B = 32'hFFFF_FFFB;  #10;

        tb_A = 32'h7FFFFFFF;tb_B = 32'hFFFFFFFF;#10;
        tb_A = 32'h80000000;tb_B = 32'd1;      #10;

        $display("--- AND Testleri (010) ---");
        tb_ALUControl = 3'b010;
        tb_A = 32'hFFFF0000;tb_B = 32'h0000FFFF;#10;
        tb_A = 32'hF0F0F0F0;tb_B = 32'h0F0F0F0F;#10;
        tb_A = 32'hABCDEF01;tb_B = 32'hFFFFFFFF;#10;

        $display("--- XOR Testleri (011) ---");
        tb_ALUControl = 3'b011;
        tb_A = 32'hFFFF0000;tb_B = 32'h0000FFFF;#10;
        tb_A = 32'hF0F0F0F0;tb_B = 32'h0F0F0F0F;#10;
        tb_A = 32'hABCDEF01;tb_B = 32'hFFFFFFFF;#10;
        tb_A = 32'd10;      tb_B = 32'd10;     #10;

        $display("--- SLT Testleri (101) ---");
        tb_ALUControl = 3'b101;
        tb_A = 32'd5;       tb_B = 32'd10;     #10;
        tb_A = 32'd10;      tb_B = 32'd5;      #10;
        tb_A = 32'hFFFF_FFFB;  tb_B = 32'd10;     #10;
        tb_A = 32'd5;       tb_B = 32'hFFFF_FFF6; #10;
        tb_A = 32'hFFFF_FFF6;  tb_B = 32'hFFFF_FFFB;  #10;
        tb_A = 32'hFFFF_FFFB;   tb_B = 32'hFFFF_FFF6; #10;
        tb_A = 32'd10;      tb_B = 32'd10;     #10;

        tb_A = 32'h80000000;tb_B = 32'h7FFFFFFF;#10;
        tb_A = 32'h7FFFFFFF;tb_B = 32'h80000000;#10;

        $display("--- Tanımsız Kontrol Kodu Testleri ---");
        tb_ALUControl = 3'b100; #10;
        tb_ALUControl = 3'b110; #10;
        tb_ALUControl = 3'b111; #10;

        #20;
        $display("--- Simülasyon Bitti ---");
        $finish;

    end

endmodule

ödev1/alu_tb.vcd
$date
	Thu Apr 17 19:13:39 2025
$end
$version
	Icarus Verilog
$end
$timescale
	1ps
$end
$scope module ALU_tb $end
$var wire 1 ! tb_oVerflow $end
$var wire 32 " tb_Result [31:0] $end
$var parameter 32 # N $end
$var reg 32 $ tb_A [31:0] $end
$var reg 3 % tb_ALUControl [2:0] $end
$var reg 32 & tb_B [31:0] $end
$scope module uut $end
$var wire 32 ' A [31:0] $end
$var wire 3 ( ALUControl [2:0] $end
$var wire 32 ) B [31:0] $end
$var wire 32 * B_operand [31:0] $end
$var wire 1 ! oVerflow $end
$var wire 32 + xor_result [31:0] $end
$var wire 32 , slt_result [31:0] $end
$var wire 32 - and_result [31:0] $end
$var wire 32 . adder_sum [31:0] $end
$var wire 1 / adder_cout $end
$var wire 32 0 Result [31:0] $end
$var wire 1 1 Cin $end
$var parameter 32 2 N $end
$scope module adder_unit $end
$var wire 32 3 A [31:0] $end
$var wire 32 4 B [31:0] $end
$var wire 1 1 Cin $end
$var wire 32 5 Sum [31:0] $end
$var wire 1 / Cout $end
$var parameter 32 6 N $end
$upscope $end
$scope module and_unit $end
$var wire 32 7 A [31:0] $end
$var wire 32 8 B [31:0] $end
$var wire 32 9 Result [31:0] $end
$var parameter 32 : N $end
$upscope $end
$scope module output_mux $end
$var wire 32 ; In_AddResult [31:0] $end
$var wire 32 < In_AndResult [31:0] $end
$var wire 32 = In_SubResult [31:0] $end
$var wire 3 > Sel [2:0] $end
$var wire 32 ? In_XorResult [31:0] $end
$var wire 32 @ In_SltResult [31:0] $end
$var parameter 32 A N $end
$var reg 32 B Out [31:0] $end
$upscope $end
$scope module slt_unit $end
$var wire 1 ! Overflow $end
$var wire 1 C Sum_MSB $end
$var wire 1 D slt_bit $end
$var wire 32 E SLT_Result [31:0] $end
$var parameter 32 F N $end
$upscope $end
$scope module xor_unit $end
$var wire 32 G A [31:0] $end
$var wire 32 H B [31:0] $end
$var wire 32 I Result [31:0] $end
$var parameter 32 J N $end
$upscope $end
$upscope $end
$upscope $end
$enddefinitions $end
$comment Show the parameter values. $end
$dumpall
b100000 J
b100000 F
b100000 A
b100000 :
b100000 6
b100000 2
b100000 #
$end
#0
$dumpvars
b0 I
b0 H
b0 G
b0 E
0D
0C
b0 B
b0 @
b0 ?
b0 >
b0 =
b0 <
b0 ;
b0 9
b0 8
b0 7
b0 5
b0 4
b0 3
01
b0 0
0/
b0 .
b0 -
b0 ,
b0 +
b0 *
b0 )
b0 (
b0 '
b0 &
b0 %
b0 $
b0 "
0!
$end
#5000
b1111 "
b1111 0
b1111 B
b101 *
b101 4
b1111 .
b1111 5
b1111 ;
b1111 =
b1111 +
b1111 ?
b1111 I
b101 &
b101 )
b101 8
b101 H
b1010 $
b1010 '
b1010 3
b1010 7
b1010 G
#15000
b101 "
b101 0
b101 B
b101 .
b101 5
b101 ;
b101 =
1/
b11111111111111111111111111111011 *
b11111111111111111111111111111011 4
b1010 -
b1010 9
b1010 <
b11111111111111111111111111110001 +
b11111111111111111111111111110001 ?
b11111111111111111111111111110001 I
b11111111111111111111111111111011 &
b11111111111111111111111111111011 )
b11111111111111111111111111111011 8
b11111111111111111111111111111011 H
#25000
b1 ,
b1 @
b1 E
1D
0/
1C
b11111111111111111111111111111011 "
b11111111111111111111111111111011 0
b11111111111111111111111111111011 B
b101 *
b101 4
b11111111111111111111111111111011 .
b11111111111111111111111111111011 5
b11111111111111111111111111111011 ;
b11111111111111111111111111111011 =
b100 -
b100 9
b100 <
b11111111111111111111111111110011 +
b11111111111111111111111111110011 ?
b11111111111111111111111111110011 I
b101 &
b101 )
b101 8
b101 H
b11111111111111111111111111110110 $
b11111111111111111111111111110110 '
b11111111111111111111111111110110 3
b11111111111111111111111111110110 7
b11111111111111111111111111110110 G
#35000
b11111111111111111111111111110001 "
b11111111111111111111111111110001 0
b11111111111111111111111111110001 B
b11111111111111111111111111110001 .
b11111111111111111111111111110001 5
b11111111111111111111111111110001 ;
b11111111111111111111111111110001 =
1/
b11111111111111111111111111111011 *
b11111111111111111111111111111011 4
b11111111111111111111111111110010 -
b11111111111111111111111111110010 9
b11111111111111111111111111110010 <
b1101 +
b1101 ?
b1101 I
b11111111111111111111111111111011 &
b11111111111111111111111111111011 )
b11111111111111111111111111111011 8
b11111111111111111111111111111011 H
#45000
1!
b0 ,
b0 @
b0 E
0D
0/
1C
b10000000000000000000000000000000 "
b10000000000000000000000000000000 0
b10000000000000000000000000000000 B
b1 *
b1 4
b10000000000000000000000000000000 .
b10000000000000000000000000000000 5
b10000000000000000000000000000000 ;
b10000000000000000000000000000000 =
b1 -
b1 9
b1 <
b1111111111111111111111111111110 +
b1111111111111111111111111111110 ?
b1111111111111111111111111111110 I
b1 &
b1 )
b1 8
b1 H
b1111111111111111111111111111111 $
b1111111111111111111111111111111 '
b1111111111111111111111111111111 3
b1111111111111111111111111111111 7
b1111111111111111111111111111111 G
#55000
b1 ,
b1 @
b1 E
1D
1!
0C
1/
b0 "
b0 0
b0 B
b10000000000000000000000000000000 *
b10000000000000000000000000000000 4
b0 .
b0 5
b0 ;
b0 =
b10000000000000000000000000000000 -
b10000000000000000000000000000000 9
b10000000000000000000000000000000 <
b0 +
b0 ?
b0 I
b10000000000000000000000000000000 &
b10000000000000000000000000000000 )
b10000000000000000000000000000000 8
b10000000000000000000000000000000 H
b10000000000000000000000000000000 $
b10000000000000000000000000000000 '
b10000000000000000000000000000000 3
b10000000000000000000000000000000 7
b10000000000000000000000000000000 G
#65000
0!
b0 ,
b0 @
b0 E
0D
0C
b101 "
b101 0
b101 B
b11111111111111111111111111111010 *
b11111111111111111111111111111010 4
b101 .
b101 5
b101 ;
b101 =
1/
b0 -
b0 9
b0 <
b1111 +
b1111 ?
b1111 I
11
b101 &
b101 )
b101 8
b101 H
b1010 $
b1010 '
b1010 3
b1010 7
b1010 G
b1 %
b1 (
b1 >
#75000
b1 ,
b1 @
b1 E
1D
1C
0/
b11111111111111111111111111111011 "
b11111111111111111111111111111011 0
b11111111111111111111111111111011 B
b11111111111111111111111111110101 *
b11111111111111111111111111110101 4
b11111111111111111111111111111011 .
b11111111111111111111111111111011 5
b11111111111111111111111111111011 ;
b11111111111111111111111111111011 =
b1010 &
b1010 )
b1010 8
b1010 H
b101 $
b101 '
b101 3
b101 7
b101 G
#85000
b0 ,
b0 @
b0 E
0D
0C
b1111 "
b1111 0
b1111 B
b100 *
b100 4
b1111 .
b1111 5
b1111 ;
b1111 =
0/
b1010 -
b1010 9
b1010 <
b11111111111111111111111111110001 +
b11111111111111111111111111110001 ?
b11111111111111111111111111110001 I
b11111111111111111111111111111011 &
b11111111111111111111111111111011 )
b11111111111111111111111111111011 8
b11111111111111111111111111111011 H
b1010 $
b1010 '
b1010 3
b1010 7
b1010 G
#95000
b1 ,
b1 @
b1 E
1D
1/
1C
b11111111111111111111111111110001 "
b11111111111111111111111111110001 0
b11111111111111111111111111110001 B
b11111111111111111111111111111010 *
b11111111111111111111111111111010 4
b11111111111111111111111111110001 .
b11111111111111111111111111110001 5
b11111111111111111111111111110001 ;
b11111111111111111111111111110001 =
b100 -
b100 9
b100 <
b11111111111111111111111111110011 +
b11111111111111111111111111110011 ?
b11111111111111111111111111110011 I
b101 &
b101 )
b101 8
b101 H
b11111111111111111111111111110110 $
b11111111111111111111111111110110 '
b11111111111111111111111111110110 3
b11111111111111111111111111110110 7
b11111111111111111111111111110110 G
#105000
b11111111111111111111111111111011 "
b11111111111111111111111111111011 0
b11111111111111111111111111111011 B
b11111111111111111111111111111011 .
b11111111111111111111111111111011 5
b11111111111111111111111111111011 ;
b11111111111111111111111111111011 =
0/
b100 *
b100 4
b11111111111111111111111111110010 -
b11111111111111111111111111110010 9
b11111111111111111111111111110010 <
b1101 +
b1101 ?
b1101 I
b11111111111111111111111111111011 &
b11111111111111111111111111111011 )
b11111111111111111111111111111011 8
b11111111111111111111111111111011 H
#115000
b0 ,
b0 @
b0 E
0D
1!
b10000000000000000000000000000000 "
b10000000000000000000000000000000 0
b10000000000000000000000000000000 B
b0 *
b0 4
b10000000000000000000000000000000 .
b10000000000000000000000000000000 5
b10000000000000000000000000000000 ;
b10000000000000000000000000000000 =
b1111111111111111111111111111111 -
b1111111111111111111111111111111 9
b1111111111111111111111111111111 <
b10000000000000000000000000000000 +
b10000000000000000000000000000000 ?
b10000000000000000000000000000000 I
b11111111111111111111111111111111 &
b11111111111111111111111111111111 )
b11111111111111111111111111111111 8
b11111111111111111111111111111111 H
b1111111111111111111111111111111 $
b1111111111111111111111111111111 '
b1111111111111111111111111111111 3
b1111111111111111111111111111111 7
b1111111111111111111111111111111 G
#125000
b1 ,
b1 @
b1 E
1D
1!
0C
1/
b1111111111111111111111111111111 "
b1111111111111111111111111111111 0
b1111111111111111111111111111111 B
b11111111111111111111111111111110 *
b11111111111111111111111111111110 4
b1111111111111111111111111111111 .
b1111111111111111111111111111111 5
b1111111111111111111111111111111 ;
b1111111111111111111111111111111 =
b0 -
b0 9
b0 <
b10000000000000000000000000000001 +
b10000000000000000000000000000001 ?
b10000000000000000000000000000001 I
b1 &
b1 )
b1 8
b1 H
b10000000000000000000000000000000 $
b10000000000000000000000000000000 '
b10000000000000000000000000000000 3
b10000000000000000000000000000000 7
b10000000000000000000000000000000 G
#135000
0!
0/
1C
b1111111111111111 *
b1111111111111111 4
b11111111111111111111111111111111 .
b11111111111111111111111111111111 5
b11111111111111111111111111111111 ;
b11111111111111111111111111111111 =
b11111111111111111111111111111111 +
b11111111111111111111111111111111 ?
b11111111111111111111111111111111 I
01
b0 "
b0 0
b0 B
b1111111111111111 &
b1111111111111111 )
b1111111111111111 8
b1111111111111111 H
b11111111111111110000000000000000 $
b11111111111111110000000000000000 '
b11111111111111110000000000000000 3
b11111111111111110000000000000000 7
b11111111111111110000000000000000 G
b10 %
b10 (
b10 >
#145000
b1111000011110000111100001111 *
b1111000011110000111100001111 4
b11111111111111111111111111111111 .
b11111111111111111111111111111111 5
b11111111111111111111111111111111 ;
b11111111111111111111111111111111 =
b1111000011110000111100001111 &
b1111000011110000111100001111 )
b1111000011110000111100001111 8
b1111000011110000111100001111 H
b11110000111100001111000011110000 $
b11110000111100001111000011110000 '
b11110000111100001111000011110000 3
b11110000111100001111000011110000 7
b11110000111100001111000011110000 G
#155000
1/
b10101011110011011110111100000001 "
b10101011110011011110111100000001 0
b10101011110011011110111100000001 B
b11111111111111111111111111111111 *
b11111111111111111111111111111111 4
b10101011110011011110111100000000 .
b10101011110011011110111100000000 5
b10101011110011011110111100000000 ;
b10101011110011011110111100000000 =
b10101011110011011110111100000001 -
b10101011110011011110111100000001 9
b10101011110011011110111100000001 <
b1010100001100100001000011111110 +
b1010100001100100001000011111110 ?
b1010100001100100001000011111110 I
b11111111111111111111111111111111 &
b11111111111111111111111111111111 )
b11111111111111111111111111111111 8
b11111111111111111111111111111111 H
b10101011110011011110111100000001 $
b10101011110011011110111100000001 '
b10101011110011011110111100000001 3
b10101011110011011110111100000001 7
b10101011110011011110111100000001 G
#165000
b11111111111111110000000000000000 *
b11111111111111110000000000000000 4
b11111111111111100000000000000001 .
b11111111111111100000000000000001 5
b11111111111111100000000000000001 ;
b11111111111111100000000000000001 =
b0 -
b0 9
b0 <
b11111111111111111111111111111111 +
b11111111111111111111111111111111 ?
b11111111111111111111111111111111 I
11
b11111111111111111111111111111111 "
b11111111111111111111111111111111 0
b11111111111111111111111111111111 B
b1111111111111111 &
b1111111111111111 )
b1111111111111111 8
b1111111111111111 H
b11111111111111110000000000000000 $
b11111111111111110000000000000000 '
b11111111111111110000000000000000 3
b11111111111111110000000000000000 7
b11111111111111110000000000000000 G
b11 %
b11 (
b11 >
#175000
b11110000111100001111000011110000 *
b11110000111100001111000011110000 4
b11100001111000011110000111100001 .
b11100001111000011110000111100001 5
b11100001111000011110000111100001 ;
b11100001111000011110000111100001 =
b1111000011110000111100001111 &
b1111000011110000111100001111 )
b1111000011110000111100001111 8
b1111000011110000111100001111 H
b11110000111100001111000011110000 $
b11110000111100001111000011110000 '
b11110000111100001111000011110000 3
b11110000111100001111000011110000 7
b11110000111100001111000011110000 G
#185000
0/
b1010100001100100001000011111110 "
b1010100001100100001000011111110 0
b1010100001100100001000011111110 B
b0 *
b0 4
b10101011110011011110111100000010 .
b10101011110011011110111100000010 5
b10101011110011011110111100000010 ;
b10101011110011011110111100000010 =
b10101011110011011110111100000001 -
b10101011110011011110111100000001 9
b10101011110011011110111100000001 <
b1010100001100100001000011111110 +
b1010100001100100001000011111110 ?
b1010100001100100001000011111110 I
b11111111111111111111111111111111 &
b11111111111111111111111111111111 )
b11111111111111111111111111111111 8
b11111111111111111111111111111111 H
b10101011110011011110111100000001 $
b10101011110011011110111100000001 '
b10101011110011011110111100000001 3
b10101011110011011110111100000001 7
b10101011110011011110111100000001 G
#195000
b0 ,
b0 @
b0 E
0D
1/
0C
b0 "
b0 0
b0 B
b11111111111111111111111111110101 *
b11111111111111111111111111110101 4
b0 .
b0 5
b0 ;
b0 =
b1010 -
b1010 9
b1010 <
b0 +
b0 ?
b0 I
b1010 &
b1010 )
b1010 8
b1010 H
b1010 $
b1010 '
b1010 3
b1010 7
b1010 G
#205000
b1 "
b1 0
b1 B
b1 ,
b1 @
b1 E
1D
1C
b11111111111111111111111111111011 .
b11111111111111111111111111111011 5
b11111111111111111111111111111011 ;
b11111111111111111111111111111011 =
0/
b0 -
b0 9
b0 <
b1111 +
b1111 ?
b1111 I
b101 $
b101 '
b101 3
b101 7
b101 G
b101 %
b101 (
b101 >
#215000
b0 "
b0 0
b0 B
b0 ,
b0 @
b0 E
0D
0C
b11111111111111111111111111111010 *
b11111111111111111111111111111010 4
b101 .
b101 5
b101 ;
b101 =
1/
b101 &
b101 )
b101 8
b101 H
b1010 $
b1010 '
b1010 3
b1010 7
b1010 G
#225000
b1 "
b1 0
b1 B
b1 ,
b1 @
b1 E
1D
1C
b11111111111111111111111111110101 *
b11111111111111111111111111110101 4
b11111111111111111111111111110001 .
b11111111111111111111111111110001 5
b11111111111111111111111111110001 ;
b11111111111111111111111111110001 =
b1010 -
b1010 9
b1010 <
b11111111111111111111111111110001 +
b11111111111111111111111111110001 ?
b11111111111111111111111111110001 I
b1010 &
b1010 )
b1010 8
b1010 H
b11111111111111111111111111111011 $
b11111111111111111111111111111011 '
b11111111111111111111111111111011 3
b11111111111111111111111111111011 7
b11111111111111111111111111111011 G
#235000
b0 "
b0 0
b0 B
b0 ,
b0 @
b0 E
0D
0!
0C
b1001 *
b1001 4
b1111 .
b1111 5
b1111 ;
b1111 =
0/
b100 -
b100 9
b100 <
b11111111111111111111111111110011 +
b11111111111111111111111111110011 ?
b11111111111111111111111111110011 I
b11111111111111111111111111110110 &
b11111111111111111111111111110110 )
b11111111111111111111111111110110 8
b11111111111111111111111111110110 H
b101 $
b101 '
b101 3
b101 7
b101 G
#245000
b1 "
b1 0
b1 B
b1 ,
b1 @
b1 E
1D
0!
1C
b100 *
b100 4
b11111111111111111111111111111011 .
b11111111111111111111111111111011 5
b11111111111111111111111111111011 ;
b11111111111111111111111111111011 =
0/
b11111111111111111111111111110010 -
b11111111111111111111111111110010 9
b11111111111111111111111111110010 <
b1101 +
b1101 ?
b1101 I
b11111111111111111111111111111011 &
b11111111111111111111111111111011 )
b11111111111111111111111111111011 8
b11111111111111111111111111111011 H
b11111111111111111111111111110110 $
b11111111111111111111111111110110 '
b11111111111111111111111111110110 3
b11111111111111111111111111110110 7
b11111111111111111111111111110110 G
#255000
b0 "
b0 0
b0 B
b0 ,
b0 @
b0 E
0D
0C
b1001 *
b1001 4
b101 .
b101 5
b101 ;
b101 =
1/
b11111111111111111111111111110110 &
b11111111111111111111111111110110 )
b11111111111111111111111111110110 8
b11111111111111111111111111110110 H
b11111111111111111111111111111011 $
b11111111111111111111111111111011 '
b11111111111111111111111111111011 3
b11111111111111111111111111111011 7
b11111111111111111111111111111011 G
#265000
b11111111111111111111111111110101 *
b11111111111111111111111111110101 4
b0 .
b0 5
b0 ;
b0 =
1/
b1010 -
b1010 9
b1010 <
b0 +
b0 ?
b0 I
b1010 &
b1010 )
b1010 8
b1010 H
b1010 $
b1010 '
b1010 3
b1010 7
b1010 G
#275000
b1 "
b1 0
b1 B
b1 ,
b1 @
b1 E
1D
1!
b10000000000000000000000000000000 *
b10000000000000000000000000000000 4
b1 .
b1 5
b1 ;
b1 =
b0 -
b0 9
b0 <
b11111111111111111111111111111111 +
b11111111111111111111111111111111 ?
b11111111111111111111111111111111 I
b1111111111111111111111111111111 &
b1111111111111111111111111111111 )
b1111111111111111111111111111111 8
b1111111111111111111111111111111 H
b10000000000000000000000000000000 $
b10000000000000000000000000000000 '
b10000000000000000000000000000000 3
b10000000000000000000000000000000 7
b10000000000000000000000000000000 G
#285000
b0 "
b0 0
b0 B
b0 ,
b0 @
b0 E
0D
1!
1C
0/
b1111111111111111111111111111111 *
b1111111111111111111111111111111 4
b11111111111111111111111111111111 .
b11111111111111111111111111111111 5
b11111111111111111111111111111111 ;
b11111111111111111111111111111111 =
b10000000000000000000000000000000 &
b10000000000000000000000000000000 )
b10000000000000000000000000000000 8
b10000000000000000000000000000000 H
b1111111111111111111111111111111 $
b1111111111111111111111111111111 '
b1111111111111111111111111111111 3
b1111111111111111111111111111111 7
b1111111111111111111111111111111 G
#295000
b1 ,
b1 @
b1 E
1D
0!
b10000000000000000000000000000000 *
b10000000000000000000000000000000 4
b11111111111111111111111111111111 .
b11111111111111111111111111111111 5
b11111111111111111111111111111111 ;
b11111111111111111111111111111111 =
01
bx "
bx 0
bx B
b100 %
b100 (
b100 >
#305000
b110 %
b110 (
b110 >
#315000
b1 ,
b1 @
b1 E
1D
1C
b1111111111111111111111111111111 *
b1111111111111111111111111111111 4
b11111111111111111111111111111111 .
b11111111111111111111111111111111 5
b11111111111111111111111111111111 ;
b11111111111111111111111111111111 =
0/
11
b111 %
b111 (
b111 >
