ödev2/Q2/data_memory.v
module data_memory (
    input  logic        clk,
    input  logic        MemWrite,    
    input  logic [31:0] Address,     
    input  logic [31:0] WriteData,
    output logic [31:0] ReadData     
);

    parameter MEM_WORDS = 1024;
    localparam ADDR_WIDTH = $clog2(MEM_WORDS); 
    logic [31:0] memory [MEM_WORDS-1:0];
    logic [ADDR_WIDTH-1:0] word_addr;
    assign word_addr = Address[ADDR_WIDTH+1:2];

    // Write Operation
    always_ff @(posedge clk) begin
        if (MemWrite) begin
            if (word_addr < MEM_WORDS) begin
                 memory[word_addr] <= WriteData;
            end
        end
    end

    // Read Operation
    assign ReadData = (word_addr < MEM_WORDS) ? memory[word_addr] : 32'bx;

endmodule

ödev2/Q1/alu.v
module alu (
    input  logic [31:0] A, B,         
    input  logic [2:0]  ALUControl,  
    output logic [31:0] Result,     
    output logic        Zero         
);

    always_comb begin
        case (ALUControl)
            3'b000: Result = A + B;                                     
            3'b001: Result = A - B;                                     
            3'b010: Result = A & B;                                     
            3'b011: Result = A | B;                                     
            3'b101: Result = ($signed(A) < $signed(B)) ? 32'd1 : 32'd0;

            default: Result = 32'bx;
        endcase
    end

    assign Zero = (Result == 32'b0);

endmodule

ödev2/immediate_generator.v
// immediate_generator.v
module immediate_generator (
    input  logic [31:0] Instruction,
    input  logic [1:0]  ImmSrc,
    output logic [31:0] ImmExt
);

    localparam I_TYPE = 2'b00;
    localparam S_TYPE = 2'b01;
    localparam B_TYPE = 2'b10;
    localparam J_TYPE = 2'b11;

    logic [31:0] imm_i_ext, imm_s_ext, imm_b_ext, imm_j_ext;
    logic [12:0] imm_b_val;
    logic [20:0] imm_j_val; 

    // I-type
    assign imm_i_ext = {{20{Instruction[31]}}, Instruction[31:20]};

    // S-type
    assign imm_s_ext = {{20{Instruction[31]}}, Instruction[31:25], Instruction[11:7]};

    // B-type
    assign imm_b_val = {Instruction[31], Instruction[7], Instruction[30:25], Instruction[11:8], 1'b0};
    assign imm_b_ext = {{19{imm_b_val[12]}}, imm_b_val};

    // J-type 
    assign imm_j_val = {Instruction[31], Instruction[19:12], Instruction[20], Instruction[30:21], 1'b0};
    assign imm_j_ext = {{11{imm_j_val[20]}}, imm_j_val};


    always_comb begin
        case (ImmSrc)
            I_TYPE:  ImmExt = imm_i_ext;
            S_TYPE:  ImmExt = imm_s_ext;
            B_TYPE:  ImmExt = imm_b_ext;
            J_TYPE:  ImmExt = imm_j_ext;
            default: ImmExt = 32'bx; 
        endcase
    end

endmodule

ödev2/Q1/register_file.v
module register_file (
    input  logic        clk,
    input  logic        RegWrite,
    input  logic [4:0]  rs1_addr, rs2_addr, rd_addr,
    input  logic [31:0] WriteData,
    output logic [31:0] ReadData1, ReadData2
);

    logic [31:0] registers [31:0];

    always_ff @(posedge clk) begin
        if (RegWrite && (rd_addr != 5'b00000)) begin 
            registers[rd_addr] <= WriteData;
        end
    end

    assign ReadData1 = (rs1_addr == 5'b00000) ? 32'b0 : registers[rs1_addr];
    assign ReadData2 = (rs2_addr == 5'b00000) ? 32'b0 : registers[rs2_addr];

endmodule

ödev2/Q1/control_unit.v
module control_unit (
    input  logic [6:0] Opcode,
    input  logic [2:0] funct3,
    input  logic       funct7b5, 

    output logic       RegWrite,
    output logic [1:0] ImmSrc,
    output logic       ALUSrc,
    output logic       MemWrite,
    output logic [1:0] ResultSrc,
    output logic       Branch,
    output logic       Jump,
    output logic [2:0] ALUControl // ALU Decoder Output
);

    // Internal signal from Main Decoder logic to ALU Decoder logic
    logic [1:0] ALUOp;

    // Main Decoder Logic
    localparam LW   = 7'b0000011;
    localparam SW   = 7'b0100011;
    localparam RTYPE = 7'b0110011;
    localparam BEQ  = 7'b1100011;
    localparam ITYPE_ALU = 7'b0010011;
    localparam JAL  = 7'b1101111;

    always_comb begin

        RegWrite  = 1'b0;
        ImmSrc    = 2'bxx;
        ALUSrc    = 1'b0;
        MemWrite  = 1'b0;
        ResultSrc = 2'bxx;
        Branch    = 1'b0;
        ALUOp     = 2'bxx; 
        Jump      = 1'b0;

        case (Opcode)
            LW: begin
                RegWrite  = 1'b1; ImmSrc = 2'b00; ALUSrc = 1'b1; MemWrite = 1'b0; ResultSrc = 2'b01; Branch = 1'b0; ALUOp = 2'b00; Jump = 1'b0;
            end
            SW: begin
                RegWrite  = 1'b0; ImmSrc = 2'b01; ALUSrc = 1'b1; MemWrite = 1'b1; ResultSrc = 2'bxx; Branch = 1'b0; ALUOp = 2'b00; Jump = 1'b0;
            end
            RTYPE: begin
                RegWrite  = 1'b1; ImmSrc = 2'bxx; ALUSrc = 1'b0; MemWrite = 1'b0; ResultSrc = 2'b00; Branch = 1'b0; ALUOp = 2'b10; Jump = 1'b0;
            end
            BEQ: begin
                RegWrite  = 1'b0; ImmSrc = 2'b10; ALUSrc = 1'b0; MemWrite = 1'b0; ResultSrc = 2'bxx; Branch = 1'b1; ALUOp = 2'b01; Jump = 1'b0;
            end
            ITYPE_ALU: begin
                RegWrite  = 1'b1; ImmSrc = 2'b00; ALUSrc = 1'b1; MemWrite = 1'b0; ResultSrc = 2'b00; Branch = 1'b0; ALUOp = 2'b10; Jump = 1'b0;
            end
            JAL: begin
                RegWrite  = 1'b1; ImmSrc = 2'b11; ALUSrc = 1'bx; MemWrite = 1'b0; ResultSrc = 2'b10; Branch = 1'b0; ALUOp = 2'bxx; Jump = 1'b1;
            end
            default: begin
            end
        endcase
    end

    // ALU Decoder Logic
    always_comb begin
        case (ALUOp)
            2'b00: ALUControl = 3'b000; // Add for Load/Store address calculation
            2'b01: ALUControl = 3'b001; // Subtract for BEQ comparison
            2'b10: begin // R-type or I-type ALU operation
                case (funct3)
                    3'b000: begin // add, sub, addi
                        if (funct7b5 == 1'b1 && Opcode == RTYPE)
                            ALUControl = 3'b001; // SUB
                        else
                            ALUControl = 3'b000; // ADD or ADDI
                    end
                    3'b010: ALUControl = 3'b101; // slt, slti
                    3'b110: ALUControl = 3'b011; // or, ori
                    3'b111: ALUControl = 3'b010; // and, andi
                    default: ALUControl = 3'bxxx;
                endcase
            end
            default: ALUControl = 3'bxxx;
        endcase
    end

endmodule

ödev2/Q1/pc_register.v
module pc_register (
    input  logic        clk,
    input  logic [31:0] NextPC,   
    output logic [31:0] PC        
);

    initial PC = 32'h00000000;

    always_ff @(posedge clk) begin
        PC <= NextPC;
    end
endmodule

ödev2/Q2/riscv_processor.v
`include "alu.v"
`include "control_unit.v"
`include "data_memory.v"
`include "immediate_generator.v"
`include "pc_register.v"
`include "register_file.v"


module riscv_processor (
    input  logic        clk,
    input  logic [31:0] Instruction,
    output logic [31:0] PC_out,
    output logic [31:0] ALUResult_out,
    output logic [31:0] Mem_ReadData_out
);

    // PC and Next PC logic
    logic [31:0] PC_current;
    logic [31:0] PC_next;
    logic [31:0] PC_plus4;
    logic [31:0] PC_target;
    logic        PCSrc;

    // Instruction fields extraction
    logic [6:0] opcode;
    logic [4:0] rs1_addr, rs2_addr, rd_addr;
    logic [2:0] funct3;
    logic       funct7b5;

    // Control Unit signals
    logic        RegWrite;
    logic [1:0]  ImmSrc;
    logic        ALUSrc;
    logic        MemWrite;
    logic [1:0]  ResultSrc;
    logic        Branch;
    logic        Jump;
    logic [2:0]  ALUControl;

    // Immediate Generator output
    logic [31:0] ImmExtended;

    // Register File outputs
    logic [31:0] Reg_ReadData1;
    logic [31:0] Reg_ReadData2;

    // ALU inputs and outputs
    logic [31:0] ALU_InputA;
    logic [31:0] ALU_InputB;
    logic [31:0] ALU_Result;
    logic        ALU_Zero;

    // Data Memory output
    logic [31:0] Mem_ReadData;

    // Result Mux output 
    logic [31:0] Result_WriteData;


    // --- Instruction Field Assignments ---
    assign opcode   = Instruction[6:0];
    assign rs1_addr = Instruction[19:15];
    assign rs2_addr = Instruction[24:20];
    assign rd_addr  = Instruction[11:7];
    assign funct3   = Instruction[14:12];
    assign funct7b5 = Instruction[30];


    // Program Counter Register Module
    pc_register pc_reg (
        .clk     (clk),
        .NextPC  (PC_next),
        .PC      (PC_current)
    );

    // Control Unit Module
    control_unit ctrl_unit (
        .Opcode    (opcode),
        .funct3    (funct3),
        .funct7b5  (funct7b5),
        .RegWrite  (RegWrite),
        .ImmSrc    (ImmSrc),
        .ALUSrc    (ALUSrc),
        .MemWrite  (MemWrite),
        .ResultSrc (ResultSrc),
        .Branch    (Branch),
        .Jump      (Jump),
        .ALUControl(ALUControl)
    );

    // Register File Module
    register_file reg_file (
        .clk       (clk),
        .RegWrite  (RegWrite),
        .rs1_addr  (rs1_addr),
        .rs2_addr  (rs2_addr),
        .rd_addr   (rd_addr),
        .WriteData (Result_WriteData), 
        .ReadData1 (Reg_ReadData1),
        .ReadData2 (Reg_ReadData2)
    );

    // Immediate Generator Module
    immediate_generator imm_gen (
        .Instruction (Instruction),
        .ImmSrc      (ImmSrc),
        .ImmExt      (ImmExtended)
    );


    assign ALU_InputA = Reg_ReadData1; // SrcA always comes from RegFile RD1
    assign ALU_InputB = ALUSrc ? ImmExtended : Reg_ReadData2; // Mux for SrcB


    alu alu_unit (
        .A          (ALU_InputA),
        .B          (ALU_InputB),
        .ALUControl (ALUControl),
        .Result     (ALU_Result),
        .Zero       (ALU_Zero)
    );


    data_memory data_mem (
        .clk       (clk),
        .MemWrite  (MemWrite),
        .Address   (ALU_Result),    
        .WriteData (Reg_ReadData2), 
        .ReadData  (Mem_ReadData)
    );


    always_comb begin
        case (ResultSrc)
            2'b00:  Result_WriteData = ALU_Result;   // R-type, I-type ALU
            2'b01:  Result_WriteData = Mem_ReadData; // lw
            2'b10:  Result_WriteData = PC_plus4;     // jal
            default: Result_WriteData = 32'bx;
        endcase
    end

    // Next PC Calculation Logic Module
    assign PC_plus4 = PC_current + 32'd4;
    assign PC_target = PC_current + ImmExtended; // For Branch/JAL

    // PCSrc Mux selection logic
    assign PCSrc = (Branch & ALU_Zero) | Jump;

    // Next PC Mux
    assign PC_next = PCSrc ? PC_target : PC_plus4;

    assign PC_out = PC_current;
    assign ALUResult_out = ALU_Result;
    assign Mem_ReadData_out = Mem_ReadData;

endmodule

ödev2/tb_riscv_processor.v
`timescale 1ns / 1ps
`include "riscv_processor.v"

module tb_riscv_processor;
    logic clk;
    logic [31:0] instruction_in;
    logic [31:0] pc_out;
    logic [31:0] alu_result_out;
    logic [31:0] mem_read_data_out;

    logic [31:0] instr_mem [0:63];

    riscv_processor dut (
        .clk          (clk),
        .Instruction  (instruction_in),
        .PC_out       (pc_out),
        .ALUResult_out(alu_result_out),
        .Mem_ReadData_out(mem_read_data_out)
    );

    initial begin
        clk = 0;
        forever #5 clk = ~clk; 
    end

    assign instruction_in = instr_mem[pc_out >> 2];

    initial begin
        instr_mem[0]  = 32'h00A00093; // addi x1, x0, 10
        instr_mem[1]  = 32'h01400113; // addi x2, x0, 20
        instr_mem[2]  = 32'h00A00193; // addi x3, x0, 10
        instr_mem[3]  = 32'h00208233; // add  x4, x1, x2
        instr_mem[4]  = 32'h401102B3; // sub  x5, x2, x1
        instr_mem[5]  = 32'h0020A333; // slt  x6, x1, x2
        instr_mem[6]  = 32'h0050E3B3; // or   x7, x1, x5
        instr_mem[7]  = 32'h0020F433; // and  x8, x1, x2
        instr_mem[8]  = 32'hFFB20493; // addi x9, x4, -5
        instr_mem[9]  = 32'h00A2A513; // slti x10, x5, 10
        instr_mem[10] = 32'h0553E593; // ori  x11, x7, 0x55
        instr_mem[11] = 32'h00F3F613; // andi x12, x7, 0x0F
        instr_mem[12] = 32'h00402423; // sw   x4, 8(x0)
        instr_mem[13] = 32'h00800683; // lw   x13, 8(x0)
        instr_mem[14] = 32'h00308663; // beq  x1, x3, +12 (L1 @ 0x44 = index 17)
        instr_mem[15] = 32'h06300713; // addi x14, x0, 99  (Skipped)
        instr_mem[16] = 32'h06300793; // addi x15, x0, 99  (Skipped)
        instr_mem[17] = 32'h00008833; // add  x16, x1, x0  (L1)
        instr_mem[18] = 32'h008000EF; // jal  x1, +8     (L2 @ 0x50 = index 20)
        instr_mem[19] = 32'h05800893; // addi x17, x0, 88  (Skipped)
        instr_mem[20] = 32'h04D00913; // addi x18, x0, 77  (L2)
        instr_mem[21] = 32'h00000063; // beq  x0, x0, 0   (loop)

        $dumpfile("wave_q1.vcd"); // VCD dosyasının adı
        $dumpvars(0, tb_riscv_processor); // Tüm sinyalleri dök

        #200; 

        $display("Simulasyon tamamlandi!");
        $finish;
    end
endmodule



// iverilog -g2012 -o sim_q1 tb_riscv_processor.v
// vvp sim_q1
// gtkwave wave_q1.vcd &

ödev2/wave_q1.vcd
$date
	Wed Apr 30 13:50:32 2025
$end
$version
	Icarus Verilog
$end
$timescale
	1ps
$end
$scope module tb_riscv_processor $end
$var wire 32 ! instruction_in [31:0] $end
$var wire 32 " pc_out [31:0] $end
$var wire 32 # mem_read_data_out [31:0] $end
$var wire 32 $ alu_result_out [31:0] $end
$var reg 1 % clk $end
$scope module dut $end
$var wire 32 & ALUResult_out [31:0] $end
$var wire 32 ' ALU_InputA [31:0] $end
$var wire 32 ( Instruction [31:0] $end
$var wire 32 ) Mem_ReadData_out [31:0] $end
$var wire 1 * PCSrc $end
$var wire 32 + PC_out [31:0] $end
$var wire 1 % clk $end
$var wire 5 , rs2_addr [4:0] $end
$var wire 5 - rs1_addr [4:0] $end
$var wire 5 . rd_addr [4:0] $end
$var wire 7 / opcode [6:0] $end
$var wire 1 0 funct7b5 $end
$var wire 3 1 funct3 [2:0] $end
$var wire 2 2 ResultSrc [1:0] $end
$var wire 32 3 Reg_ReadData2 [31:0] $end
$var wire 32 4 Reg_ReadData1 [31:0] $end
$var wire 1 5 RegWrite $end
$var wire 32 6 PC_target [31:0] $end
$var wire 32 7 PC_plus4 [31:0] $end
$var wire 32 8 PC_next [31:0] $end
$var wire 32 9 PC_current [31:0] $end
$var wire 32 : Mem_ReadData [31:0] $end
$var wire 1 ; MemWrite $end
$var wire 1 < Jump $end
$var wire 2 = ImmSrc [1:0] $end
$var wire 32 > ImmExtended [31:0] $end
$var wire 1 ? Branch $end
$var wire 1 @ ALU_Zero $end
$var wire 32 A ALU_Result [31:0] $end
$var wire 32 B ALU_InputB [31:0] $end
$var wire 1 C ALUSrc $end
$var wire 3 D ALUControl [2:0] $end
$var reg 32 E Result_WriteData [31:0] $end
$scope module alu_unit $end
$var wire 32 F A [31:0] $end
$var wire 32 G B [31:0] $end
$var wire 1 @ Zero $end
$var wire 3 H ALUControl [2:0] $end
$var reg 32 I Result [31:0] $end
$upscope $end
$scope module ctrl_unit $end
$var wire 7 J Opcode [6:0] $end
$var wire 3 K funct3 [2:0] $end
$var wire 1 0 funct7b5 $end
$var parameter 7 L BEQ $end
$var parameter 7 M ITYPE_ALU $end
$var parameter 7 N JAL $end
$var parameter 7 O LW $end
$var parameter 7 P RTYPE $end
$var parameter 7 Q SW $end
$var reg 3 R ALUControl [2:0] $end
$var reg 2 S ALUOp [1:0] $end
$var reg 1 C ALUSrc $end
$var reg 1 ? Branch $end
$var reg 2 T ImmSrc [1:0] $end
$var reg 1 < Jump $end
$var reg 1 ; MemWrite $end
$var reg 1 5 RegWrite $end
$var reg 2 U ResultSrc [1:0] $end
$upscope $end
$scope module data_mem $end
$var wire 32 V Address [31:0] $end
$var wire 1 ; MemWrite $end
$var wire 1 % clk $end
$var wire 10 W word_addr [9:0] $end
$var wire 32 X WriteData [31:0] $end
$var wire 32 Y ReadData [31:0] $end
$var parameter 32 Z ADDR_WIDTH $end
$var parameter 32 [ MEM_WORDS $end
$upscope $end
$scope module imm_gen $end
$var wire 2 \ ImmSrc [1:0] $end
$var wire 32 ] Instruction [31:0] $end
$var wire 32 ^ imm_s_ext [31:0] $end
$var wire 21 _ imm_j_val [20:0] $end
$var wire 32 ` imm_j_ext [31:0] $end
$var wire 32 a imm_i_ext [31:0] $end
$var wire 13 b imm_b_val [12:0] $end
$var wire 32 c imm_b_ext [31:0] $end
$var parameter 2 d B_TYPE $end
$var parameter 2 e I_TYPE $end
$var parameter 2 f J_TYPE $end
$var parameter 2 g S_TYPE $end
$var reg 32 h ImmExt [31:0] $end
$upscope $end
$scope module pc_reg $end
$var wire 32 i NextPC [31:0] $end
$var wire 1 % clk $end
$var reg 32 j PC [31:0] $end
$upscope $end
$scope module reg_file $end
$var wire 1 5 RegWrite $end
$var wire 32 k WriteData [31:0] $end
$var wire 1 % clk $end
$var wire 5 l rd_addr [4:0] $end
$var wire 5 m rs1_addr [4:0] $end
$var wire 5 n rs2_addr [4:0] $end
$var wire 32 o ReadData2 [31:0] $end
$var wire 32 p ReadData1 [31:0] $end
$upscope $end
$upscope $end
$upscope $end
$enddefinitions $end
$comment Show the parameter values. $end
$dumpall
b1 g
b11 f
b0 e
b10 d
b10000000000 [
b1010 Z
b100011 Q
b110011 P
b11 O
b1101111 N
b10011 M
b1100011 L
$end
#0
$dumpvars
b0 p
bx o
b1010 n
b0 m
b1 l
b1010 k
b0 j
b100 i
b1010 h
b100000000000 c
b100000000000 b
b1010 a
b1010 `
b1010 _
b1 ^
b101000000000000010010011 ]
b0 \
bx Y
bx X
b10 W
b1010 V
b0 U
b0 T
b10 S
b0 R
b0 K
b10011 J
b1010 I
b0 H
b1010 G
b0 F
b1010 E
b0 D
1C
b1010 B
b1010 A
0@
0?
b1010 >
b0 =
0<
0;
bx :
b0 9
b100 8
b100 7
b1010 6
15
b0 4
bx 3
b0 2
b0 1
00
b10011 /
b1 .
b0 -
b1010 ,
b0 +
0*
bx )
b101000000000000010010011 (
b0 '
b1010 &
0%
b1010 $
bx #
b0 "
b101000000000000010010011 !
$end
#5000
b101 W
b10100 E
b10100 k
b10100 $
b10100 &
b10100 A
b10100 I
b10100 V
b10100 B
b10100 G
b10100 >
b10100 h
b10100 ,
b10100 n
b10 .
b10 l
b10100 a
b10 ^
b10 c
b10 b
b10100 `
b10100 _
b1000 8
b1000 i
b1010000000000000100010011 !
b1010000000000000100010011 (
b1010000000000000100010011 ]
b11000 6
b1000 7
b100 "
b100 +
b100 9
b100 j
1%
#10000
0%
#15000
b10 W
b1010 E
b1010 k
b1010 $
b1010 &
b1010 A
b1010 I
b1010 V
b1010 B
b1010 G
b1010 >
b1010 h
b1010 ,
b1010 n
b11 .
b11 l
b1010 a
b11 ^
b100000000010 c
b100000000010 b
b1010 `
b1010 _
b1100 8
b1100 i
b101000000000000110010011 !
b101000000000000110010011 (
b101000000000000110010011 ]
b10010 6
b1100 7
b1000 "
b1000 +
b1000 9
b1000 j
1%
#20000
0%
#25000
b111 W
b11110 E
b11110 k
b11110 $
b11110 &
b11110 A
b11110 I
b11110 V
b10100 B
b10100 G
b10 S
b0 2
b0 U
0C
bx =
bx T
bx \
15
b1010 '
b1010 F
b1010 4
b1010 p
b10100 3
b10100 X
b10100 o
bx >
bx h
b110011 /
b110011 J
b1 -
b1 m
b10 ,
b10 n
b100 .
b100 l
b10 a
b100 ^
b100 c
b100 b
b1000000000000010 `
b1000000000000010 _
b10000 8
b10000 i
b1000001000001000110011 !
b1000001000001000110011 (
b1000001000001000110011 ]
bx 6
b10000 7
b1100 "
b1100 +
b1100 9
b1100 j
1%
#30000
0%
#35000
b10 W
b1010 E
b1010 k
b1010 B
b1010 G
0@
b1010 $
b1010 &
b1010 A
b1010 I
b1010 V
b10100 '
b10100 F
b10100 4
b10100 p
b1010 3
b1010 X
b1010 o
b1 D
b1 H
b1 R
b10 -
b10 m
b1 ,
b1 n
b101 .
b101 l
10
b10000000001 a
b10000000101 ^
b110000000100 c
b110000000100 b
b10000110000000000 `
b10000110000000000 _
b10100 8
b10100 i
b1000000000100010000001010110011 !
b1000000000100010000001010110011 (
b1000000000100010000001010110011 ]
b10100 7
b10000 "
b10000 +
b10000 9
b10000 j
1%
#40000
0%
#45000
b0 W
b1 E
b1 k
b10100 B
b10100 G
0@
b1 $
b1 &
b1 A
b1 I
b1 V
b1010 '
b1010 F
b1010 4
b1010 p
b10100 3
b10100 X
b10100 o
b101 D
b101 H
b101 R
b1 -
b1 m
b10 ,
b10 n
b110 .
b110 l
b10 1
b10 K
00
b10 a
b110 ^
b110 c
b110 b
b1010000000000010 `
b1010000000000010 _
b11000 8
b11000 i
b1000001010001100110011 !
b1000001010001100110011 (
b1000001010001100110011 ]
b11000 7
b10100 "
b10100 +
b10100 9
b10100 j
1%
#50000
0%
#55000
b10 W
b1010 E
b1010 k
b1010 B
b1010 G
b1010 $
b1010 &
b1010 A
b1010 I
b1010 V
b1010 3
b1010 X
b1010 o
b11 D
b11 H
b11 R
b101 ,
b101 n
b111 .
b111 l
b110 1
b110 K
b101 a
b111 ^
b100000000110 c
b100000000110 b
b1110100000000100 `
b1110100000000100 _
b11100 8
b11100 i
b10100001110001110110011 !
b10100001110001110110011 (
b10100001110001110110011 ]
b11100 7
b11000 "
b11000 +
b11000 9
b11000 j
1%
#60000
0%
#65000
b0 W
b0 E
b0 k
1@
b0 $
b0 &
b0 A
b0 I
b0 V
b10100 B
b10100 G
b10100 3
b10100 X
b10100 o
b10 D
b10 H
b10 R
b10 ,
b10 n
b1000 .
b1000 l
b111 1
b111 K
b10 a
b1000 ^
b1000 c
b1000 b
b1111000000000010 `
b1111000000000010 _
b100000 8
b100000 i
b1000001111010000110011 !
b1000001111010000110011 (
b1000001111010000110011 ]
b100000 7
b11100 "
b11100 +
b11100 9
b11100 j
1%
#70000
0%
#75000
b110 W
b11001 E
b11001 k
b11111111111111111111111111111011 B
b11111111111111111111111111111011 G
0@
b11001 $
b11001 &
b11001 A
b11001 I
b11001 V
b11011 6
b11111111111111111111111111111011 >
b11111111111111111111111111111011 h
1C
b0 =
b0 T
b0 \
b10 S
b0 2
b0 U
15
b11110 '
b11110 F
b11110 4
b11110 p
bx 3
bx X
bx o
b0 D
b0 H
b0 R
b10011 /
b10011 J
b100 -
b100 m
b11011 ,
b11011 n
b1001 .
b1001 l
b0 1
b0 K
10
b11111111111111111111111111111011 a
b11111111111111111111111111101001 ^
b11111111111111111111111111101000 c
b1111111101000 b
b11111111111100100000111111111010 `
b100100000111111111010 _
b100100 8
b100100 i
b11111111101100100000010010010011 !
b11111111101100100000010010010011 (
b11111111101100100000010010010011 ]
b100100 7
b100000 "
b100000 +
b100000 9
b100000 j
1%
#80000
0%
#85000
b0 W
b0 E
b0 k
1@
b0 $
b0 &
b0 A
b0 I
b0 V
b1010 B
b1010 G
b1010 '
b1010 F
b1010 4
b1010 p
b101 D
b101 H
b101 R
b1010 >
b1010 h
b101 -
b101 m
b1010 ,
b1010 n
b1010 .
b1010 l
b10 1
b10 K
00
b1010 a
b1010 ^
b1010 c
b1010 b
b101010000000001010 `
b101010000000001010 _
b101000 8
b101000 i
b101000101010010100010011 !
b101000101010010100010011 (
b101000101010010100010011 ]
b101110 6
b101000 7
b100100 "
b100100 +
b100100 9
b100100 j
1%
#90000
0%
#95000
b10111 W
b1011111 E
b1011111 k
0@
b1011111 $
b1011111 &
b1011111 A
b1011111 I
b1011111 V
b1010101 B
b1010101 G
b11 D
b11 H
b11 R
b1010101 >
b1010101 h
b111 -
b111 m
b10101 ,
b10101 n
b1011 .
b1011 l
b110 1
b110 K
b1010101 a
b1001011 ^
b100001001010 c
b100001001010 b
b111110100001010100 `
b111110100001010100 _
bx 3
bx X
bx o
b101100 8
b101100 i
b101010100111110010110010011 !
b101010100111110010110010011 (
b101010100111110010110010011 ]
b1111101 6
b101100 7
b101000 "
b101000 +
b101000 9
b101000 j
1%
#100000
0%
#105000
b10 W
b1010 E
b1010 k
b1010 $
b1010 &
b1010 A
b1010 I
b1010 V
b1111 B
b1111 G
b10 D
b10 H
b10 R
b1111 >
b1111 h
b1111 ,
b1111 n
b1100 .
b1100 l
b111 1
b111 K
b1111 a
b1100 ^
b1100 c
b1100 b
b111111100000001110 `
b111111100000001110 _
b110000 8
b110000 i
b111100111111011000010011 !
b111100111111011000010011 (
b111100111111011000010011 ]
b111011 6
b110000 7
b101100 "
b101100 +
b101100 9
b101100 j
1%
#110000
0%
#115000
b10 W
bx E
bx k
b1000 $
b1000 &
b1000 A
b1000 I
b1000 V
b1000 B
b1000 G
1;
b0 S
bx 2
bx U
1C
b1 =
b1 T
b1 \
05
b0 '
b0 F
b0 4
b0 p
b11110 3
b11110 X
b11110 o
b0 D
b0 H
b0 R
b1000 >
b1000 h
b100011 /
b100011 J
b0 -
b0 m
b100 ,
b100 n
b1000 .
b1000 l
b10 1
b10 K
b100 a
b1000 ^
b1000 c
b1000 b
b10000000000100 `
b10000000000100 _
b110100 8
b110100 i
b10000000010010000100011 !
b10000000010010000100011 (
b10000000010010000100011 ]
b111000 6
b110100 7
b110000 "
b110000 +
b110000 9
b110000 j
1%
#120000
0%
#125000
b10 W
b1000 $
b1000 &
b1000 A
b1000 I
b1000 V
b11110 E
b11110 k
b1000 B
b1000 G
b1 2
b1 U
15
b0 S
0;
1C
b0 =
b0 T
b0 \
b0 3
b0 X
b0 o
b1000 >
b1000 h
b11 /
b11 J
b1000 ,
b1000 n
b1101 .
b1101 l
b0 1
b0 K
b1000 a
b1101 ^
b100000001100 c
b100000001100 b
b1000 `
b1000 _
b111000 8
b111000 i
b100000000000011010000011 !
b100000000000011010000011 (
b100000000000011010000011 ]
b11110 #
b11110 )
b11110 :
b11110 Y
b111100 6
b111000 7
b110100 "
b110100 +
b110100 9
b110100 j
1%
#130000
0%
#135000
bx #
bx )
bx :
bx Y
1*
b0 W
bx E
bx k
1@
b0 $
b0 &
b0 A
b0 I
b0 V
b1010 B
b1010 G
b1 D
b1 H
b1 R
1?
b1 S
bx 2
bx U
0C
b10 =
b10 T
b10 \
05
b1010 '
b1010 F
b1010 4
b1010 p
b1010 3
b1010 X
b1010 o
b1100 >
b1100 h
b1100011 /
b1100011 J
b1 -
b1 m
b11 ,
b11 n
b1100 .
b1100 l
b11 a
b1100 ^
b1100 c
b1100 b
b1000100000000010 `
b1000100000000010 _
b1000100 8
b1000100 i
b1100001000011001100011 !
b1100001000011001100011 (
b1100001000011001100011 ]
b1000100 6
b111100 7
b111000 "
b111000 +
b111000 9
b111000 j
1%
#140000
0%
#145000
b11110 #
b11110 )
b11110 :
b11110 Y
b10 W
0*
0@
b1010 $
b1010 &
b1010 A
b1010 I
b1010 V
b1010 E
b1010 k
b0 B
b0 G
b0 D
b0 H
b0 R
b0 2
b0 U
15
b10 S
0?
bx =
bx T
bx \
b0 3
b0 X
b0 o
bx >
bx h
b110011 /
b110011 J
b0 ,
b0 n
b10000 .
b10000 l
b0 a
b10000 ^
b10000 c
b10000 b
b1000000000000000 `
b1000000000000000 _
b1001000 8
b1001000 i
b1000100000110011 !
b1000100000110011 (
b1000100000110011 ]
bx 6
b1001000 7
b1000100 "
b1000100 +
b1000100 9
b1000100 j
1%
#150000
0%
#155000
bx #
bx )
bx :
bx Y
bx W
1*
b0x000 B
b0x000 G
b1010000 6
b1000 >
b1000 h
b1001100 E
b1001100 k
x@
bx $
bx &
bx A
bx I
bx V
bx D
bx H
bx R
1<
xC
b11 =
b11 T
b11 \
bx S
b10 2
b10 U
15
b0 '
b0 F
b0 4
b0 p
b1101111 /
b1101111 J
b0 -
b0 m
b1000 ,
b1000 n
b1 .
b1 l
b1000 a
b1 ^
b100000000000 c
b100000000000 b
b1000 `
b1000 _
b1010000 8
b1010000 i
b100000000000000011101111 !
b100000000000000011101111 (
b100000000000000011101111 ]
b1001100 7
b1001000 "
b1001000 +
b1001000 9
b1001000 j
1%
#160000
0%
#165000
b10011 W
0@
b1001101 $
b1001101 &
b1001101 A
b1001101 I
b1001101 V
0*
b1001101 B
b1001101 G
b0 D
b0 H
b0 R
b10 S
0<
b0 2
b0 U
1C
b0 =
b0 T
b0 \
15
b11110 3
b11110 X
b11110 o
b1001101 >
b1001101 h
b10011 /
b10011 J
b1101 ,
b1101 n
b10010 .
b10010 l
b1001101 a
b1010010 ^
b1010010 c
b1010010 b
b100001001100 `
b100001001100 _
b1010100 8
b1010100 i
b1001101 E
b1001101 k
b100110100000000100100010011 !
b100110100000000100100010011 (
b100110100000000100100010011 ]
b10011101 6
b1010100 7
b1010000 "
b1010000 +
b1010000 9
b1010000 j
1%
#170000
0%
#175000
1*
b0 W
1@
b0 $
b0 &
b0 A
b0 I
b0 V
bx E
bx k
b0 B
b0 G
b1 D
b1 H
b1 R
1?
b1 S
bx 2
bx U
0C
b10 =
b10 T
b10 \
05
b0 3
b0 X
b0 o
b0 >
b0 h
b1100011 /
b1100011 J
b0 ,
b0 n
b0 .
b0 l
b0 a
b0 ^
b0 c
b0 b
b0 `
b0 _
b1010100 8
b1010100 i
b1100011 !
b1100011 (
b1100011 ]
b1010100 6
b1011000 7
b1010100 "
b1010100 +
b1010100 9
b1010100 j
1%
