ödev2/Q2/data_memory.v
module data_memory (
    input  logic        clk,
    input  logic        MemWrite,    
    input  logic [31:0] Address,     
    input  logic [31:0] WriteData,
    output logic [31:0] ReadData     
);

    parameter MEM_WORDS = 1024;
    localparam ADDR_WIDTH = $clog2(MEM_WORDS); 
    logic [31:0] memory [MEM_WORDS-1:0];
    logic [ADDR_WIDTH-1:0] word_addr;
    assign word_addr = Address[ADDR_WIDTH+1:2];

    // Write Operation
    always_ff @(posedge clk) begin
        if (MemWrite) begin
            if (word_addr < MEM_WORDS) begin
                 memory[word_addr] <= WriteData;
            end
        end
    end

    // Read Operation
    assign ReadData = (word_addr < MEM_WORDS) ? memory[word_addr] : 32'bx;

endmodule

ödev2/Q3/alu.v
module alu (
    input  logic [31:0] A, B,
    input  logic [2:0]  ALUControl,
    output logic [31:0] Result,
    output logic        Zero
);

    logic [4:0] shift_amount; 
    assign shift_amount = B[4:0];

    always_comb begin
        case (ALUControl)
            3'b000: Result = A + B;                                     // ADD (for L/S, add, addi)
            3'b001: Result = A - B;                                     // SUB (for beq, sub)
            3'b010: Result = A & B;                                     // AND (for and, andi)
            3'b011: Result = A | B;                                     // OR  (for or, ori)
            3'b100: Result = A << shift_amount;                               // <<< NEW: SLL
            3'b101: Result = ($signed(A) < $signed(B)) ? 32'd1 : 32'd0; // SLT (for slt, slti)
            default: Result = 32'bx;
        endcase
    end

    assign Zero = (Result == 32'b0);

endmodule

ödev2/immediate_generator.v
// immediate_generator.v
module immediate_generator (
    input  logic [31:0] Instruction,
    input  logic [1:0]  ImmSrc,
    output logic [31:0] ImmExt
);

    localparam I_TYPE = 2'b00;
    localparam S_TYPE = 2'b01;
    localparam B_TYPE = 2'b10;
    localparam J_TYPE = 2'b11;

    logic [31:0] imm_i_ext, imm_s_ext, imm_b_ext, imm_j_ext;
    logic [12:0] imm_b_val;
    logic [20:0] imm_j_val; 

    // I-type
    assign imm_i_ext = {{20{Instruction[31]}}, Instruction[31:20]};

    // S-type
    assign imm_s_ext = {{20{Instruction[31]}}, Instruction[31:25], Instruction[11:7]};

    // B-type
    assign imm_b_val = {Instruction[31], Instruction[7], Instruction[30:25], Instruction[11:8], 1'b0};
    assign imm_b_ext = {{19{imm_b_val[12]}}, imm_b_val};

    // J-type 
    assign imm_j_val = {Instruction[31], Instruction[19:12], Instruction[20], Instruction[30:21], 1'b0};
    assign imm_j_ext = {{11{imm_j_val[20]}}, imm_j_val};


    always_comb begin
        case (ImmSrc)
            I_TYPE:  ImmExt = imm_i_ext;
            S_TYPE:  ImmExt = imm_s_ext;
            B_TYPE:  ImmExt = imm_b_ext;
            J_TYPE:  ImmExt = imm_j_ext;
            default: ImmExt = 32'bx; 
        endcase
    end

endmodule

ödev2/Q1/register_file.v
module register_file (
    input  logic        clk,
    input  logic        RegWrite,
    input  logic [4:0]  rs1_addr, rs2_addr, rd_addr,
    input  logic [31:0] WriteData,
    output logic [31:0] ReadData1, ReadData2
);

    logic [31:0] registers [31:0];

    always_ff @(posedge clk) begin
        if (RegWrite && (rd_addr != 5'b00000)) begin 
            registers[rd_addr] <= WriteData;
        end
    end

    assign ReadData1 = (rs1_addr == 5'b00000) ? 32'b0 : registers[rs1_addr];
    assign ReadData2 = (rs2_addr == 5'b00000) ? 32'b0 : registers[rs2_addr];

endmodule

ödev2/Q2/control_unit.v
module control_unit (
    input  logic [6:0] Opcode,
    input  logic [2:0] funct3,
    input  logic       funct7b5,

    output logic       RegWrite,
    output logic [1:0] ImmSrc,
    output logic       ALUSrc,
    output logic       MemWrite,
    output logic [1:0] ResultSrc,
    output logic       Branch,
    output logic       Jump,
    output logic [2:0] ALUControl
);

    logic [1:0] ALUOp;

    localparam LW   = 7'b0000011;
    localparam SW   = 7'b0100011;
    localparam RTYPE = 7'b0110011;
    localparam BEQ  = 7'b1100011;
    localparam ITYPE_ALU = 7'b0010011;
    localparam JAL  = 7'b1101111;

    always_comb begin

        RegWrite  = 1'b0; ImmSrc    = 2'bxx; ALUSrc    = 1'b0;
        MemWrite  = 1'b0; ResultSrc = 2'bxx; Branch    = 1'b0;
        ALUOp     = 2'bxx; Jump      = 1'b0;

        case (Opcode)
            LW: begin
                RegWrite  = 1'b1; ImmSrc = 2'b00; ALUSrc = 1'b1; MemWrite = 1'b0; ResultSrc = 2'b01; Branch = 1'b0; ALUOp = 2'b00; Jump = 1'b0;
            end
            SW: begin
                RegWrite  = 1'b0; ImmSrc = 2'b01; ALUSrc = 1'b1; MemWrite = 1'b1; ResultSrc = 2'bxx; Branch = 1'b0; ALUOp = 2'b00; Jump = 1'b0;
            end
            RTYPE: begin // Covers add, sub, slt, or, and, SLL
                RegWrite  = 1'b1; ImmSrc = 2'bxx; ALUSrc = 1'b0; MemWrite = 1'b0; ResultSrc = 2'b00; Branch = 1'b0; ALUOp = 2'b10; Jump = 1'b0;
            end
            BEQ: begin
                RegWrite  = 1'b0; ImmSrc = 2'b10; ALUSrc = 1'b0; MemWrite = 1'b0; ResultSrc = 2'bxx; Branch = 1'b1; ALUOp = 2'b01; Jump = 1'b0;
            end
            ITYPE_ALU: begin // Covers addi, slti, ori, andi
                RegWrite  = 1'b1; ImmSrc = 2'b00; ALUSrc = 1'b1; MemWrite = 1'b0; ResultSrc = 2'b00; Branch = 1'b0; ALUOp = 2'b10; Jump = 1'b0;
            end
            JAL: begin
                RegWrite  = 1'b1; ImmSrc = 2'b11; ALUSrc = 1'bx; MemWrite = 1'b0; ResultSrc = 2'b10; Branch = 1'b0; ALUOp = 2'bxx; Jump = 1'b1;
            end
            default: begin 
                RegWrite  = 1'b0; ImmSrc = 2'bxx; ALUSrc = 1'b0;
                MemWrite  = 1'b0; ResultSrc = 2'bxx; Branch = 1'b0;
                ALUOp     = 2'bxx; Jump      = 1'b0;
            end
        endcase
    end


    always_comb begin
        case (ALUOp)
            2'b00: ALUControl = 3'b000;
            2'b01: ALUControl = 3'b001;
            2'b10: begin // R-type or I-type ALU operation
                case (funct3)
                    3'b000: begin // add, sub, addi
                        if (funct7b5 == 1'b1 && Opcode == RTYPE)
                            ALUControl = 3'b001; // SUB
                        else
                            ALUControl = 3'b000; // ADD or ADDI
                    end
                    3'b001: ALUControl = 3'b100; // <<< NEW: SLL (funct3 = 001 for R-Type)
                    3'b010: ALUControl = 3'b101; // slt, slti
                    3'b110: ALUControl = 3'b011; // or, ori
                    3'b111: ALUControl = 3'b010; // and, andi
                    default: ALUControl = 3'bxxx;
                endcase
            end
            default: ALUControl = 3'bxxx;
        endcase
    end

endmodule

ödev2/Q1/pc_register.v
module pc_register (
    input  logic        clk,
    input  logic [31:0] NextPC,   
    output logic [31:0] PC        
);

    initial PC = 32'h00000000;

    always_ff @(posedge clk) begin
        PC <= NextPC;
    end
endmodule

ödev2/Q2/riscv_processor.v
`include "alu.v"
`include "control_unit.v"
`include "data_memory.v"
`include "immediate_generator.v"
`include "pc_register.v"
`include "register_file.v"


module riscv_processor (
    input  logic        clk,
    input  logic [31:0] Instruction,
    output logic [31:0] PC_out,
    output logic [31:0] ALUResult_out,
    output logic [31:0] Mem_ReadData_out
);

    // PC and Next PC logic
    logic [31:0] PC_current;
    logic [31:0] PC_next;
    logic [31:0] PC_plus4;
    logic [31:0] PC_target;
    logic        PCSrc;

    // Instruction fields extraction
    logic [6:0] opcode;
    logic [4:0] rs1_addr, rs2_addr, rd_addr;
    logic [2:0] funct3;
    logic       funct7b5;

    // Control Unit signals
    logic        RegWrite;
    logic [1:0]  ImmSrc;
    logic        ALUSrc;
    logic        MemWrite;
    logic [1:0]  ResultSrc;
    logic        Branch;
    logic        Jump;
    logic [2:0]  ALUControl;

    // Immediate Generator output
    logic [31:0] ImmExtended;

    // Register File outputs
    logic [31:0] Reg_ReadData1;
    logic [31:0] Reg_ReadData2;

    // ALU inputs and outputs
    logic [31:0] ALU_InputA;
    logic [31:0] ALU_InputB;
    logic [31:0] ALU_Result;
    logic        ALU_Zero;

    // Data Memory output
    logic [31:0] Mem_ReadData;

    // Result Mux output 
    logic [31:0] Result_WriteData;


    // --- Instruction Field Assignments ---
    assign opcode   = Instruction[6:0];
    assign rs1_addr = Instruction[19:15];
    assign rs2_addr = Instruction[24:20];
    assign rd_addr  = Instruction[11:7];
    assign funct3   = Instruction[14:12];
    assign funct7b5 = Instruction[30];


    // Program Counter Register Module
    pc_register pc_reg (
        .clk     (clk),
        .NextPC  (PC_next),
        .PC      (PC_current)
    );

    // Control Unit Module
    control_unit ctrl_unit (
        .Opcode    (opcode),
        .funct3    (funct3),
        .funct7b5  (funct7b5),
        .RegWrite  (RegWrite),
        .ImmSrc    (ImmSrc),
        .ALUSrc    (ALUSrc),
        .MemWrite  (MemWrite),
        .ResultSrc (ResultSrc),
        .Branch    (Branch),
        .Jump      (Jump),
        .ALUControl(ALUControl)
    );

    // Register File Module
    register_file reg_file (
        .clk       (clk),
        .RegWrite  (RegWrite),
        .rs1_addr  (rs1_addr),
        .rs2_addr  (rs2_addr),
        .rd_addr   (rd_addr),
        .WriteData (Result_WriteData), 
        .ReadData1 (Reg_ReadData1),
        .ReadData2 (Reg_ReadData2)
    );

    // Immediate Generator Module
    immediate_generator imm_gen (
        .Instruction (Instruction),
        .ImmSrc      (ImmSrc),
        .ImmExt      (ImmExtended)
    );


    assign ALU_InputA = Reg_ReadData1; // SrcA always comes from RegFile RD1
    assign ALU_InputB = ALUSrc ? ImmExtended : Reg_ReadData2; // Mux for SrcB


    alu alu_unit (
        .A          (ALU_InputA),
        .B          (ALU_InputB),
        .ALUControl (ALUControl),
        .Result     (ALU_Result),
        .Zero       (ALU_Zero)
    );


    data_memory data_mem (
        .clk       (clk),
        .MemWrite  (MemWrite),
        .Address   (ALU_Result),    
        .WriteData (Reg_ReadData2), 
        .ReadData  (Mem_ReadData)
    );


    always_comb begin
        case (ResultSrc)
            2'b00:  Result_WriteData = ALU_Result;   // R-type, I-type ALU
            2'b01:  Result_WriteData = Mem_ReadData; // lw
            2'b10:  Result_WriteData = PC_plus4;     // jal
            default: Result_WriteData = 32'bx;
        endcase
    end

    // Next PC Calculation Logic Module
    assign PC_plus4 = PC_current + 32'd4;
    assign PC_target = PC_current + ImmExtended; // For Branch/JAL

    // PCSrc Mux selection logic
    assign PCSrc = (Branch & ALU_Zero) | Jump;

    // Next PC Mux
    assign PC_next = PCSrc ? PC_target : PC_plus4;

    assign PC_out = PC_current;
    assign ALUResult_out = ALU_Result;
    assign Mem_ReadData_out = Mem_ReadData;

endmodule

ödev2/Q2/tb_riscv_processor_q2.v
`timescale 1ns / 1ps
`include "riscv_processor.v"

module tb_riscv_processor_q2;

    logic clk;
    logic [31:0] instruction_in;
    logic [31:0] pc_out;
    logic [31:0] alu_result_out;
    logic [31:0] mem_read_data_out;

    logic [31:0] instr_mem [0:63];

    riscv_processor dut (
        .clk          (clk),
        .Instruction  (instruction_in),
        .PC_out       (pc_out),
        .ALUResult_out(alu_result_out),
        .Mem_ReadData_out(mem_read_data_out)
    );

    initial begin
        clk = 0;
        forever #5 clk = ~clk;
    end

    assign instruction_in = instr_mem[pc_out >> 2];

    initial begin
        // Test Case 1: Simple shift
        instr_mem[0]  = 32'h00500093; // addi x1, x0, 5     (x1 = 5)
        instr_mem[1]  = 32'h00200113; // addi x2, x0, 2     (x2 = 2)
        instr_mem[2]  = 32'h002091B3; // sll  x3, x1, x2     (x3 = 5 << 2 = 20)

        // Test Case 2: Shift amount > 31
        // x1 = 5
        instr_mem[3]  = 32'h02300213; // addi x4, x0, 35    (x4 = 35)
        instr_mem[4]  = 32'h004092B3; // sll  x5, x1, x4     (x5 = 5 << (35&31)=3 = 40)

        // Test Case 3: Shift result is zero
        instr_mem[5]  = 32'h00000093; // addi x1, x0, 0     (x1 = 0)
        instr_mem[6]  = 32'h00209333; // sll  x6, x1, x2     (x6 = 0 << 2 = 0)

        // Test Case 4: Large shift amount
        instr_mem[7]  = 32'h00100093; // addi x1, x0, 1     (x1 = 1)
        instr_mem[8]  = 32'h01F00113; // addi x2, x0, 31    (x2 = 31)
        instr_mem[9]  = 32'h002093B3; // sll  x7, x1, x2     (x7 = 1 << 31 = 0x80000000)

        $dumpfile("wave_q2.vcd");
        $dumpvars(0, tb_riscv_processor_q2);

        #100;

        $display("Simulasyon tamamlandi!");
        $finish;
    end

endmodule

// iverilog -g2012 -o sim_q2 tb_riscv_processor_q2.v
// vvp sim_q2
// gtkwave wave_q2.vcd &

ödev2/Q2/wave_q2.vcd
$date
	Fri May 02 16:50:40 2025
$end
$version
	Icarus Verilog
$end
$timescale
	1ps
$end
$scope module tb_riscv_processor_q2 $end
$var wire 32 ! instruction_in [31:0] $end
$var wire 32 " pc_out [31:0] $end
$var wire 32 # mem_read_data_out [31:0] $end
$var wire 32 $ alu_result_out [31:0] $end
$var reg 1 % clk $end
$scope module dut $end
$var wire 32 & ALUResult_out [31:0] $end
$var wire 32 ' ALU_InputA [31:0] $end
$var wire 32 ( Instruction [31:0] $end
$var wire 32 ) Mem_ReadData_out [31:0] $end
$var wire 1 * PCSrc $end
$var wire 32 + PC_out [31:0] $end
$var wire 1 % clk $end
$var wire 5 , rs2_addr [4:0] $end
$var wire 5 - rs1_addr [4:0] $end
$var wire 5 . rd_addr [4:0] $end
$var wire 7 / opcode [6:0] $end
$var wire 1 0 funct7b5 $end
$var wire 3 1 funct3 [2:0] $end
$var wire 2 2 ResultSrc [1:0] $end
$var wire 32 3 Reg_ReadData2 [31:0] $end
$var wire 32 4 Reg_ReadData1 [31:0] $end
$var wire 1 5 RegWrite $end
$var wire 32 6 PC_target [31:0] $end
$var wire 32 7 PC_plus4 [31:0] $end
$var wire 32 8 PC_next [31:0] $end
$var wire 32 9 PC_current [31:0] $end
$var wire 32 : Mem_ReadData [31:0] $end
$var wire 1 ; MemWrite $end
$var wire 1 < Jump $end
$var wire 2 = ImmSrc [1:0] $end
$var wire 32 > ImmExtended [31:0] $end
$var wire 1 ? Branch $end
$var wire 1 @ ALU_Zero $end
$var wire 32 A ALU_Result [31:0] $end
$var wire 32 B ALU_InputB [31:0] $end
$var wire 1 C ALUSrc $end
$var wire 3 D ALUControl [2:0] $end
$var reg 32 E Result_WriteData [31:0] $end
$scope module alu_unit $end
$var wire 32 F A [31:0] $end
$var wire 32 G B [31:0] $end
$var wire 5 H shift_amount [4:0] $end
$var wire 1 @ Zero $end
$var wire 3 I ALUControl [2:0] $end
$var reg 32 J Result [31:0] $end
$upscope $end
$scope module ctrl_unit $end
$var wire 7 K Opcode [6:0] $end
$var wire 3 L funct3 [2:0] $end
$var wire 1 0 funct7b5 $end
$var parameter 7 M BEQ $end
$var parameter 7 N ITYPE_ALU $end
$var parameter 7 O JAL $end
$var parameter 7 P LW $end
$var parameter 7 Q RTYPE $end
$var parameter 7 R SW $end
$var reg 3 S ALUControl [2:0] $end
$var reg 2 T ALUOp [1:0] $end
$var reg 1 C ALUSrc $end
$var reg 1 ? Branch $end
$var reg 2 U ImmSrc [1:0] $end
$var reg 1 < Jump $end
$var reg 1 ; MemWrite $end
$var reg 1 5 RegWrite $end
$var reg 2 V ResultSrc [1:0] $end
$upscope $end
$scope module data_mem $end
$var wire 32 W Address [31:0] $end
$var wire 1 ; MemWrite $end
$var wire 1 % clk $end
$var wire 10 X word_addr [9:0] $end
$var wire 32 Y WriteData [31:0] $end
$var wire 32 Z ReadData [31:0] $end
$var parameter 32 [ ADDR_WIDTH $end
$var parameter 32 \ MEM_WORDS $end
$upscope $end
$scope module imm_gen $end
$var wire 2 ] ImmSrc [1:0] $end
$var wire 32 ^ Instruction [31:0] $end
$var wire 32 _ imm_s_ext [31:0] $end
$var wire 21 ` imm_j_val [20:0] $end
$var wire 32 a imm_j_ext [31:0] $end
$var wire 32 b imm_i_ext [31:0] $end
$var wire 13 c imm_b_val [12:0] $end
$var wire 32 d imm_b_ext [31:0] $end
$var parameter 2 e B_TYPE $end
$var parameter 2 f I_TYPE $end
$var parameter 2 g J_TYPE $end
$var parameter 2 h S_TYPE $end
$var reg 32 i ImmExt [31:0] $end
$upscope $end
$scope module pc_reg $end
$var wire 32 j NextPC [31:0] $end
$var wire 1 % clk $end
$var reg 32 k PC [31:0] $end
$upscope $end
$scope module reg_file $end
$var wire 1 5 RegWrite $end
$var wire 32 l WriteData [31:0] $end
$var wire 1 % clk $end
$var wire 5 m rd_addr [4:0] $end
$var wire 5 n rs1_addr [4:0] $end
$var wire 5 o rs2_addr [4:0] $end
$var wire 32 p ReadData2 [31:0] $end
$var wire 32 q ReadData1 [31:0] $end
$upscope $end
$upscope $end
$upscope $end
$enddefinitions $end
$comment Show the parameter values. $end
$dumpall
b1 h
b11 g
b0 f
b10 e
b10000000000 \
b1010 [
b100011 R
b110011 Q
b11 P
b1101111 O
b10011 N
b1100011 M
$end
#0
$dumpvars
b0 q
bx p
b101 o
b0 n
b1 m
b101 l
b0 k
b100 j
b101 i
b100000000000 d
b100000000000 c
b101 b
b100000000100 a
b100000000100 `
b1 _
b10100000000000010010011 ^
b0 ]
bx Z
bx Y
b1 X
b101 W
b0 V
b0 U
b10 T
b0 S
b0 L
b10011 K
b101 J
b0 I
b101 H
b101 G
b0 F
b101 E
b0 D
1C
b101 B
b101 A
0@
0?
b101 >
b0 =
0<
0;
bx :
b0 9
b100 8
b100 7
b101 6
15
b0 4
bx 3
b0 2
b0 1
00
b10011 /
b1 .
b0 -
b101 ,
b0 +
0*
bx )
b10100000000000010010011 (
b0 '
b101 &
0%
b101 $
bx #
b0 "
b10100000000000010010011 !
$end
#5000
b0 X
b10 E
b10 l
b10 $
b10 &
b10 A
b10 J
b10 W
b10 H
b10 B
b10 G
b10 >
b10 i
b10 ,
b10 o
b10 .
b10 m
b10 b
b10 _
b10 d
b10 c
b10 a
b10 `
b1000 8
b1000 j
b1000000000000100010011 !
b1000000000000100010011 (
b1000000000000100010011 ^
b110 6
b1000 7
b100 "
b100 +
b100 9
b100 k
1%
#10000
0%
#15000
b101 X
b10100 E
b10100 l
bx >
bx i
b10100 $
b10100 &
b10100 A
b10100 J
b10100 W
b10 T
b0 2
b0 V
0C
bx =
bx U
bx ]
15
b101 '
b101 F
b101 4
b101 q
b100 D
b100 I
b100 S
b110011 /
b110011 K
b1 -
b1 n
b11 .
b11 m
b1 1
b1 L
b11 _
b100000000010 d
b100000000010 c
b1001000000000010 a
b1001000000000010 `
b10 3
b10 Y
b10 p
b1100 8
b1100 j
b1000001001000110110011 !
b1000001001000110110011 (
b1000001001000110110011 ^
bx 6
b1100 7
b1000 "
b1000 +
b1000 9
b1000 k
1%
#20000
0%
#25000
0@
b11 H
b1000 X
b101111 6
b100011 >
b100011 i
b100011 E
b100011 l
b100011 B
b100011 G
b100011 $
b100011 &
b100011 A
b100011 J
b100011 W
1C
b0 =
b0 U
b0 ]
b10 T
b0 2
b0 V
15
b0 '
b0 F
b0 4
b0 q
b10100 3
b10100 Y
b10100 p
b0 D
b0 I
b0 S
b10011 /
b10011 K
b0 -
b0 n
b11 ,
b11 o
b100 .
b100 m
b0 1
b0 L
b100011 b
b100100 _
b100100 d
b100100 c
b100000100010 a
b100000100010 `
b10000 8
b10000 j
b10001100000000001000010011 !
b10001100000000001000010011 (
b10001100000000001000010011 ^
b10000 7
b1100 "
b1100 +
b1100 9
b1100 k
1%
#30000
0%
#35000
b1010 X
b101000 E
b101000 l
b101000 $
b101000 &
b101000 A
b101000 J
b101000 W
b10 T
b0 2
b0 V
0C
bx =
bx U
bx ]
15
b101 '
b101 F
b101 4
b101 q
b100011 3
b100011 Y
b100011 p
b100 D
b100 I
b100 S
bx >
bx i
b110011 /
b110011 K
b1 -
b1 n
b100 ,
b100 o
b101 .
b101 m
b1 1
b1 L
b100 b
b101 _
b100000000100 d
b100000000100 c
b1001000000000100 a
b1001000000000100 `
b10100 8
b10100 j
b10000001001001010110011 !
b10000001001001010110011 (
b10000001001001010110011 ^
bx 6
b10100 7
b10000 "
b10000 +
b10000 9
b10000 k
1%
#40000
0%
#45000
1@
b0 H
b0 X
b10100 6
b0 >
b0 i
b0 E
b0 l
b0 B
b0 G
b0 $
b0 &
b0 A
b0 J
b0 W
1C
b0 =
b0 U
b0 ]
b10 T
b0 2
b0 V
15
b0 '
b0 F
b0 4
b0 q
b0 3
b0 Y
b0 p
b0 D
b0 I
b0 S
b10011 /
b10011 K
b0 -
b0 n
b0 ,
b0 o
b1 .
b1 m
b0 1
b0 L
b0 b
b1 _
b100000000000 d
b100000000000 c
b0 a
b0 `
b11000 8
b11000 j
b10010011 !
b10010011 (
b10010011 ^
b11000 7
b10100 "
b10100 +
b10100 9
b10100 k
1%
#50000
0%
#55000
b10 H
b10 B
b10 G
b10 T
b0 2
b0 V
0C
bx =
bx U
bx ]
15
b10 3
b10 Y
b10 p
b100 D
b100 I
b100 S
bx >
bx i
b110011 /
b110011 K
b1 -
b1 n
b10 ,
b10 o
b110 .
b110 m
b1 1
b1 L
b10 b
b110 _
b110 d
b110 c
b1001000000000010 a
b1001000000000010 `
b11100 8
b11100 j
b1000001001001100110011 !
b1000001001001100110011 (
b1000001001001100110011 ^
bx 6
b11100 7
b11000 "
b11000 +
b11000 9
b11000 k
1%
#60000
0%
#65000
b0 X
b1 H
b11101 6
b1 >
b1 i
b1 E
b1 l
b1 B
b1 G
0@
b1 $
b1 &
b1 A
b1 J
b1 W
1C
b0 =
b0 U
b0 ]
b10 T
b0 2
b0 V
15
b0 3
b0 Y
b0 p
b0 D
b0 I
b0 S
b10011 /
b10011 K
b0 -
b0 n
b1 ,
b1 o
b1 .
b1 m
b0 1
b0 L
b1 b
b1 _
b100000000000 d
b100000000000 c
b100000000000 a
b100000000000 `
b100000 8
b100000 j
b100000000000010010011 !
b100000000000010010011 (
b100000000000010010011 ^
b100000 7
b11100 "
b11100 +
b11100 9
b11100 k
1%
#70000
0%
#75000
b111 X
b11111 E
b11111 l
b11111 $
b11111 &
b11111 A
b11111 J
b11111 W
b11111 H
b11111 B
b11111 G
b11111 >
b11111 i
b11111 ,
b11111 o
b10 .
b10 m
b11111 b
b10 _
b10 d
b10 c
b100000011110 a
b100000011110 `
bx 3
bx Y
bx p
b100100 8
b100100 j
b1111100000000000100010011 !
b1111100000000000100010011 (
b1111100000000000100010011 ^
b111111 6
b100100 7
b100000 "
b100000 +
b100000 9
b100000 k
1%
#80000
0%
#85000
b0 X
b10000000000000000000000000000000 E
b10000000000000000000000000000000 l
b10000000000000000000000000000000 $
b10000000000000000000000000000000 &
b10000000000000000000000000000000 A
b10000000000000000000000000000000 J
b10000000000000000000000000000000 W
b10 T
b0 2
b0 V
0C
bx =
bx U
bx ]
15
b1 '
b1 F
b1 4
b1 q
b11111 3
b11111 Y
b11111 p
b100 D
b100 I
b100 S
bx >
bx i
b110011 /
b110011 K
b1 -
b1 n
b10 ,
b10 o
b111 .
b111 m
b1 1
b1 L
b10 b
b111 _
b100000000110 d
b100000000110 c
b1001000000000010 a
b1001000000000010 `
b101000 8
b101000 j
b1000001001001110110011 !
b1000001001001110110011 (
b1000001001001110110011 ^
bx 6
b101000 7
b100100 "
b100100 +
b100100 9
b100100 k
1%
#90000
0%
#95000
bx H
bx X
bx E
bx l
bx B
bx G
x@
bx $
bx &
bx A
bx J
bx W
bx T
bx 2
bx V
05
bx '
bx F
bx 4
bx q
bx 3
bx Y
bx p
bx D
bx I
bx S
bx /
bx K
bx -
bx n
bx ,
bx o
bx .
bx m
bx 1
bx L
x0
bx b
bx _
bx0 d
bx0 c
bx0 a
bx0 `
b101100 8
b101100 j
bx !
bx (
bx ^
b101100 7
b101000 "
b101000 +
b101000 9
b101000 k
1%
